beanbot.py
beanbot-0.1.0.dist-info/LICENSE
beanbot-0.1.0.dist-info/WHEEL
beanbot-0.1.0.dist-info/METADATA
beanbot-0.1.0.dist-info/RECORD
