Metadata-Version: 2.1
Name: beanbot
Version: 0.1.0
Summary: 
License: MIT
Author: Kevin Zúñiga
Author-email: kevin.zun@gmail.com
Requires-Python: >=3.8,<4.0
Classifier: License :: OSI Approved :: MIT License
Classifier: Programming Language :: Python :: 3
Classifier: Programming Language :: Python :: 3.8
Requires-Dist: django (>=2.2.7,<3.0.0)
Requires-Dist: python-telegram-bot (>=12.2.0,<13.0.0)
Requires-Dist: pytz (>=2019.3,<2020.0)
